rwkit/__init__.py
rwkit/common.py
rwkit/io_json.py
rwkit/io_text.py
rwkit/io_yaml.py
rwkit-2.0.0.dist-info/LICENSE
rwkit-2.0.0.dist-info/METADATA
rwkit-2.0.0.dist-info/WHEEL
rwkit-2.0.0.dist-info/RECORD
