Metadata-Version: 2.1
Name: rwkit
Version: 2.0.0
Summary: Simplified reading & writing files with support for compression
Home-page: https://github.com/neural-tools/rwkit
License: Apache-2.0
Keywords: io,compression,json,jsonl,yaml
Author: David Adametz
Author-email: 20501597+david-adametz@users.noreply.github.com
Requires-Python: >=3.8,<4.0
Classifier: License :: OSI Approved :: Apache Software License
Classifier: Programming Language :: Python :: 3
Classifier: Programming Language :: Python :: 3.8
Classifier: Programming Language :: Python :: 3.9
Classifier: Programming Language :: Python :: 3.10
Classifier: Programming Language :: Python :: 3.11
Classifier: Programming Language :: Python :: 3.12
Provides-Extra: yaml
Provides-Extra: zstd
Requires-Dist: pyyaml (>=5.1.2) ; extra == "yaml"
Requires-Dist: zstandard (>=0.15.0) ; extra == "zstd"
Project-URL: Repository, https://github.com/neural-tools/rwkit
